Metadata-Version: 2.1
Name: pandablob
Version: 0.0.3
Summary: Functions to easily transform Azure blobs into pandas DataFrames and vice versa.
Home-page: https://github.com/uijl/pandablob
Author: Joris den Uijl
Author-email: jorisdenuijl@gmail.com
License: UNKNOWN
Keywords: pandablob,pandas,blob,Microsoft Azure Storage
Platform: any
Classifier: Natural Language :: English
Classifier: Programming Language :: Python :: 3
Classifier: Operating System :: OS Independent
